---
type: concept
tags:
  - java
  - jvm
  - class-file
  - bytecode
summary: "Class 文件是 JVM 执行引擎的入口，采用紧凑的二进制格式定义类型与行为"
sources:
  - "[[30-sources/books/深入理解Java虚拟机]]"
  - "raw/books/深入理解Java虚拟机：JVM高级特性与最佳实践（第3版）周志明.pdf"
aliases:
  - Class文件格式
  - 字节码文件
status: evolving
confidence: 0.9
updated: "2026-04-28 10:00:00"
---

# 概念_Class文件结构

## 定义

Class 文件是一组以 8 位字节为基础单位的二进制流，各数据项目紧凑排列，无分隔符。采用**平台中立 + 语言无关**设计，任何遵循规范的语言编译成的 Class 文件均可在 JVM 上执行。

## 结构概览

| 组成部分 | 说明 |
|----------|------|
| **魔数** | 0xCAFEBABE，标识 Class 文件格式 |
| **版本号** | minor_version + major_version（如 52 = JDK 8） |
| **常量池** | 字面量 + 符号引用，17 种常量类型 |
| **访问标志** | ACC_PUBLIC / ACC_FINAL / ACC_ABSTRACT 等 |
| **类/父类/接口索引** | 指向常量池的索引 |
| **字段表集合** | access_flags + name_index + descriptor_index + attributes |
| **方法表集合** | access_flags + name_index + descriptor_index + attributes（含 Code 属性） |
| **属性表集合** | Code / Exceptions / StackMapTable / Signature 等 |

### 魔数与版本号：十六进制查看

Class 文件开头的 8 个字节固定为魔数和版本号：

```bash
# 编译一个简单类
cat > TestClass.java <<'EOF'
public class TestClass {
    private int x = 42;
    public int getX() { return x; }
}
EOF
javac TestClass.java

# 十六进制转储前 32 字节
xxd TestClass.class | head -n 2
```

输出解读：

```
00000000: cafe babe 0000 0034 0016 0a00 0400 1109  .......4........
00000010: 0003 0012 0700 1307 0014 0100 0169 0100  ...............i..
```

- `cafe babe`：魔数，唯一标识 Class 文件格式
- `0000`：minor_version = 0
- `0034`：major_version = 52（JDK 8），JDK 17 为 `003d`(61)，JDK 21 为 `0041`(65)

### 方法描述符格式

JVM 内部用紧凑的**字段描述符**表示类型和方法签名，不依赖 Java 源代码名称：

| 描述符 | Java 类型 |
|--------|-----------|
| `B` `C` `S` `I` `J` `F` `D` `Z` | byte, char, short, int, long, float, double, boolean |
| `Ljava/lang/String;` | String（对象类型用 L...; 包裹） |
| `[I` `[[Ljava/lang/String;` | int[]、String[][]（数组前缀 [） |
| `(II)I` | 方法 int add(int, int) |
| `(Ljava/lang/String;)V` | 方法 void println(String) |
| `()Ljava/lang/Object;` | 方法 Object get() |
| `(IDLjava/lang/String;)J` | 方法 long f(int, double, String) |

方法描述符规则：`(参数描述符*)返回值描述符`，无参数时括号内为空。

### 常量池样例

```java
/**
 * 编译后用 javap -verbose 查看常量池
 * 每个 #数字 是一项常量：Class、Methodref、NameAndType、Utf8 等
 */
public class Sample {
    private int counter = 0;

    public void increment() {
        counter++;  // 生成 Methodref、Fieldref 引用
    }

    public static void main(String[] args) {
        System.out.println("Hello, Constant Pool!");
        // 常量池中包含 String "Hello, Constant Pool!" 的 Utf8 常量
    }
}
```

编译并反编译：

```bash
javac Sample.java
javap -verbose -p Sample.class
```

javap 常量池节选（带标注）：

```
Constant pool:
   #1 = Methodref    #7.#27   // java/lang/Object."<init>":()V
   #2 = Fieldref     #6.#28   // Sample.counter:I
   #3 = Fieldref     #29.#30  // java/lang/System.out:Ljava/io/PrintStream;
   #4 = String       #31      // "Hello, Constant Pool!"
   #5 = Methodref    #32.#33  // java/io/PrintStream.println(Ljava/lang/String;)V

  #30 = NameAndType  #38:#39  // out:Ljava/io/PrintStream;
  #33 = NameAndType  #42:#43  // println:(Ljava/lang/String;)V
  #43 = Utf8         (Ljava/lang/String;)V
```

常量池是 Class 文件最复杂的部分，大小占整个文件的 60% 以上。每个符号引用（类名、方法名、字段名、字符串字面量）都驻留在常量池中。

### javap -verbose 完整演练：方法 Code 属性

以 `increment()` 为例，javap 输出的 Code 属性片段：

```
public void increment();
  descriptor: ()V
  flags: (0x0001) ACC_PUBLIC
  Code:
    stack=3, locals=1, args_size=1
       0: aload_0
       1: dup
       2: getfield      #2    // Field counter:I
       5: iconst_1
       6: iadd
       7: putfield      #2    // Field counter:I
      10: return
    LineNumberTable:
      line 7: 0
      line 8: 10
    StackMapTable: number_of_entries = 1
      frame_type = 252 /* append */
```

逐条解读：

| 偏移 | 指令 | 说明 |
|------|------|------|
| 0 | `aload_0` | 将局部变量表第 0 位（this）压入操作数栈 |
| 1 | `dup` | 复制栈顶（this 需用于 getfield + putfield 两次） |
| 2 | `getfield #2` | 获取 counter 当前值并压栈 |
| 5 | `iconst_1` | 将常量 1 压栈 |
| 6 | `iadd` | 弹出栈顶两个 int 相加再将结果压栈 |
| 7 | `putfield #2` | 将栈顶值写回 counter 字段 |
| 10 | `return` | 方法返回 |

`stack=3, locals=1, args_size=1`：操作数栈最大深度 3（this + 原值 + 1），局部变量表 1 Slot（this），参数大小 1（this 在非 static 方法中隐式传入）。

## 字节码指令（11 大类）

加载存储、算术运算、类型转换、对象创建与访问、操作数栈管理、控制转移、方法调用（5 条：invokevirtual / invokeinterface / invokespecial / invokestatic / invokedynamic）、方法返回、异常处理、同步

### 运行时 Class 生成：ASM 动态创建类

```java
import org.objectweb.asm.*;

import java.io.FileOutputStream;
import java.lang.reflect.Method;

/**
 * 使用 ASM 直接输出字节码生成一个完整类
 * 等价于：
 *   public class AsmHello { public void sayHello() { System.out.println("ASM!"); } }
 *
 * Maven: <dependency>
 *   <groupId>org.ow2.asm</groupId>
 *   <artifactId>asm</artifactId><version>9.6</version></dependency>
 */
public class AsmClassGenerator {
    public static byte[] generate() {
        ClassWriter cw = new ClassWriter(ClassWriter.COMPUTE_FRAMES);

        // public class AsmHello extends java.lang.Object
        cw.visit(Opcodes.V1_8, Opcodes.ACC_PUBLIC,
            "AsmHello", null, "java/lang/Object", null);

        // 空构造器 public <init>()V
        MethodVisitor mv = cw.visitMethod(Opcodes.ACC_PUBLIC, "<init>", "()V", null, null);
        mv.visitCode();
        mv.visitVarInsn(Opcodes.ALOAD, 0);             // this
        mv.visitMethodInsn(Opcodes.INVOKESPECIAL,
            "java/lang/Object", "<init>", "()V", false); // super()
        mv.visitInsn(Opcodes.RETURN);
        mv.visitMaxs(0, 0);
        mv.visitEnd();

        // public void sayHello()
        mv = cw.visitMethod(Opcodes.ACC_PUBLIC, "sayHello", "()V", null, null);
        mv.visitCode();
        mv.visitFieldInsn(Opcodes.GETSTATIC,
            "java/lang/System", "out", "Ljava/io/PrintStream;");
        mv.visitLdcInsn("Hello from ASM!");
        mv.visitMethodInsn(Opcodes.INVOKEVIRTUAL,
            "java/io/PrintStream", "println", "(Ljava/lang/String;)V", false);
        mv.visitInsn(Opcodes.RETURN);
        mv.visitMaxs(0, 0);
        mv.visitEnd();

        cw.visitEnd();
        return cw.toByteArray();
    }

    public static void main(String[] args) throws Exception {
        byte[] classBytes = generate();

        // 写入 .class 文件可选，直接 defineClass 即可
        // try (FileOutputStream fos = new FileOutputStream("AsmHello.class")) {
        //     fos.write(classBytes);
        // }

        // 运行时加载并调用
        Class<?> clz = new ClassLoader() {
            Class<?> define(byte[] b) { return defineClass(null, b, 0, b.length); }
        }.define(classBytes);

        Object instance = clz.getDeclaredConstructor().newInstance();
        Method sayHello = clz.getDeclaredMethod("sayHello");
        sayHello.invoke(instance);  // 输出: Hello from ASM!
    }
}
```

ASM 的核心用法：`ClassWriter` 生成类结构，`MethodVisitor.visitXxxInsn()` 按字节码指令顺序写入方法体。`COMPUTE_FRAMES` 自动计算 StackMapTable 和 maxs，无需手动计算栈帧。

## 属性表扩展

JDK 5→12 共新增 20+ 属性：泛型签名（Signature）、模块化（Module/NestHost/NestMember）、动态常量（ConstantDynamic）等。

## 在本知识库中的应用

- 分析类版本冲突：用 `javap -verbose` 查看 major_version 确认 JDK 版本
- 理解语法糖本质：反编译 Class 文件查看泛型擦除、自动装箱的编译结果
- [[10-domains/java/jvm/概念_类加载机制]] 以 Class 文件为输入

## 关联

- [[10-domains/java/jvm/概念_类加载机制]] — Class 文件是类加载机制的输入，加载阶段从此二进制流中提取类型元数据
- [[10-domains/java/jvm/概念_字节码执行引擎]] — 方法表中的 Code 属性包含字节码指令，是执行引擎的输入
- [[10-domains/java/jvm/概念_Java语法糖]] — 语法糖的编译结果体现在 Class 文件结构中（如 Signature 属性保留泛型信息）
